LICENSE
journey_planner_python/__init__.py
journey_planner_python/computation/__init__.py
journey_planner_python/computation/route_planning.py
journey_planner_python/config/__init__.py
journey_planner_python/config/constants.py
journey_planner_python/integrations/__init__.py
journey_planner_python/integrations/google_maps.py
journey_planner_python/interface/__init__.py
journey_planner_python/interface/command_line.py
journey_planner_python/logs/__init__.py
journey_planner_python/logs/setup_logging.py
journey_planner_python/main.py
journey_planner_python/py.typed
journey_planner_python/VERSION
journey_planner_python-0.1.4.dist-info/entry_points.txt
journey_planner_python-0.1.4.dist-info/LICENSE
journey_planner_python-0.1.4.dist-info/METADATA
journey_planner_python-0.1.4.dist-info/WHEEL
journey_planner_python-0.1.4.dist-info/RECORD
